{
    "_doc": "Tunable rule inputs for engagement/classify/rules.py. Edit freely; no code change needed.",
    "generic_praise_substrings": [
        "great post",
        "great insights",
        "great share",
        "great point",
        "great points",
        "thanks for sharing",
        "thank you for sharing",
        "couldn't agree more",
        "could not agree more",
        "spot on",
        "well said",
        "well put",
        "love this",
        "love it",
        "this is gold",
        "absolutely",
        "100%",
        "100 %",
        "💯",
        "🙌",
        "👏",
        "🔥",
        "powerful message",
        "powerful post",
        "valuable insights",
        "valuable insight",
        "important reminder",
        "great reminder",
        "needed to hear this",
        "needed to read this",
        "this resonates",
        "really resonates",
        "deeply resonates",
        "thanks for the inspiration",
        "thanks for the reminder",
        "couldn't have said it better",
        "could not have said it better",
        "brilliantly put",
        "beautifully said",
        "beautifully written",
        "wise words",
        "great wisdom",
        "such wisdom",
        "key takeaway",
        "important point",
        "crucial point"
    ],
    "rules": {
        "blacklist_weight": 1.0,
        "whitelist_weight": -1.0,
        "generic_praise_threshold_hits": 1,
        "generic_praise_weight": 0.35,
        "short_comment_max_chars": 60,
        "short_comment_weight": 0.15,
        "no_personal_token_weight": 0.10,
        "emoji_only_weight": 0.40,
        "exact_text_duplicate_weight": 0.60,
        "sub_2_min_weight": 0.20,
        "ai_classification_threshold": 0.50,
        "local_model_ai_threshold": 0.70,
        "local_model_min_train_per_class": 20
    },
    "reply_templates": {
        "like_and_thanks": [
            "Thanks {first_name}! 🙏",
            "Appreciate it, {first_name}!",
            "Thanks for stopping by, {first_name}!"
        ]
    },
    "personal_tokens": [
        "you",
        "your",
        "i ",
        "i'",
        "i’",
        "me ",
        "my "
    ]
}
